leanblueprint/__init__.py
leanblueprint/client.py
leanblueprint/Packages/__init__.py
leanblueprint/Packages/blueprint.py
leanblueprint/Packages/renderer_templates/blueprint.jinja2s
leanblueprint/jekyll_templates/404.html
leanblueprint/jekyll_templates/Gemfile
leanblueprint/jekyll_templates/Gemfile.lock
leanblueprint/jekyll_templates/_config.yml
leanblueprint/jekyll_templates/index.md
leanblueprint/jekyll_templates/_include/mathjax.html
leanblueprint/jekyll_templates/_layouts/default.html
leanblueprint/jekyll_templates/assets/css/style.scss
leanblueprint/static/blueprint.css
leanblueprint/templates/blueprint.sty
leanblueprint/templates/blueprint.yml
leanblueprint/templates/content.tex
leanblueprint/templates/extra_styles.css
leanblueprint/templates/latexmkrc
leanblueprint/templates/plastex.cfg
leanblueprint/templates/print.tex
leanblueprint/templates/web.tex
leanblueprint/templates/macros/common.tex
leanblueprint/templates/macros/print.tex
leanblueprint/templates/macros/web.tex
leanblueprint-0.0.17.dist-info/licenses/LICENSE
leanblueprint-0.0.17.dist-info/licenses/NOTICE
leanblueprint-0.0.17.dist-info/METADATA
leanblueprint-0.0.17.dist-info/WHEEL
leanblueprint-0.0.17.dist-info/entry_points.txt
leanblueprint-0.0.17.dist-info/top_level.txt
leanblueprint-0.0.17.dist-info/RECORD
