Metadata-Version: 2.4
Name: leanblueprint
Version: 0.0.17
Summary: Lean prover blueprint plasTeX plugin.
Home-page: https://github.com/PatrickMassot/leanblueprint
Author: Patrick Massot
Classifier: Programming Language :: Python :: 3
Classifier: License :: OSI Approved :: MIT License
Classifier: Operating System :: OS Independent
Requires-Python: >=3.7
License-File: LICENSE
License-File: NOTICE
Requires-Dist: plasTeX>=3.1
Requires-Dist: plastexshowmore>=0.0.2
Requires-Dist: plastexdepgraph>=0.0.4
Requires-Dist: click
Requires-Dist: rich
Requires-Dist: rich-click
Requires-Dist: tomlkit
Requires-Dist: Jinja2>=3.1.0
Requires-Dist: GitPython>=3.1.28
Dynamic: license-file
